{
	"info": {
		"_postman_id": "4b38616f-6b41-4074-ac93-7d6e77deaf27",
		"name": "Labefy",
		"schema": "https://schema.getpostman.com/json/collection/v2.1.0/collection.json"
	},
	"item": [
		{
			"name": "AllPlaylists",
			"protocolProfileBehavior": {
				"disableBodyPruning": true
			},
			"request": {
				"method": "GET",
				"header": [
					{
						"key": "Authorization",
						"value": "Ayla-silva-banu",
						"type": "text"
					}
				],
				"body": {
					"mode": "raw",
					"raw": "",
					"options": {
						"raw": {
							"language": "json"
						}
					}
				},
				"url": {
					"raw": "https://us-central1-labenu-apis.cloudfunctions.net/labefy/playlists",
					"protocol": "https",
					"host": [
						"us-central1-labenu-apis",
						"cloudfunctions",
						"net"
					],
					"path": [
						"labefy",
						"playlists"
					]
				}
			},
			"response": []
		},
		{
			"name": "create playlist",
			"request": {
				"method": "POST",
				"header": [
					{
						"key": "Authorization",
						"value": "Ayla-silva-banu",
						"type": "text"
					}
				],
				"body": {
					"mode": "raw",
					"raw": "{\r\n    \"name\": \"Remix\"\r\n}",
					"options": {
						"raw": {
							"language": "json"
						}
					}
				},
				"url": {
					"raw": "https://us-central1-labenu-apis.cloudfunctions.net/labefy/playlists",
					"protocol": "https",
					"host": [
						"us-central1-labenu-apis",
						"cloudfunctions",
						"net"
					],
					"path": [
						"labefy",
						"playlists"
					]
				}
			},
			"response": []
		},
		{
			"name": "AddPlaylists",
			"request": {
				"method": "POST",
				"header": [
					{
						"key": "Authorization",
						"value": "Ayla-silva-banu",
						"type": "text"
					}
				],
				"body": {
					"mode": "raw",
					"raw": "{\r\n    \"name\":\"Yeah 3x\",\r\n    \"artist\" : \"Chris Brown\",\r\n    \"url\" :\"https://www.youtube.com/watch?v=3mC2ixOAivA\"\r\n\r\n\r\n}",
					"options": {
						"raw": {
							"language": "json"
						}
					}
				},
				"url": {
					"raw": "https://us-central1-labenu-apis.cloudfunctions.net/labefy/playlists/:playlistId/tracks",
					"protocol": "https",
					"host": [
						"us-central1-labenu-apis",
						"cloudfunctions",
						"net"
					],
					"path": [
						"labefy",
						"playlists",
						":playlistId",
						"tracks"
					],
					"variable": [
						{
							"key": "playlistId",
							"value": "71cb81c8-eaeb-4874-b433-4a476ff93d37"
						}
					]
				}
			},
			"response": []
		},
		{
			"name": "PlaylistTracks",
			"protocolProfileBehavior": {
				"disableBodyPruning": true
			},
			"request": {
				"method": "GET",
				"header": [
					{
						"key": "Authorization",
						"value": "Ayla-silva-banu",
						"type": "text"
					}
				],
				"body": {
					"mode": "raw",
					"raw": "",
					"options": {
						"raw": {
							"language": "json"
						}
					}
				},
				"url": {
					"raw": "https://us-central1-labenu-apis.cloudfunctions.net/labefy/playlists/:playlistId/tracks",
					"protocol": "https",
					"host": [
						"us-central1-labenu-apis",
						"cloudfunctions",
						"net"
					],
					"path": [
						"labefy",
						"playlists",
						":playlistId",
						"tracks"
					],
					"variable": [
						{
							"key": "playlistId",
							"value": "71cb81c8-eaeb-4874-b433-4a476ff93d37"
						}
					]
				}
			},
			"response": []
		},
		{
			"name": "searchPlaylists",
			"protocolProfileBehavior": {
				"disableBodyPruning": true
			},
			"request": {
				"method": "GET",
				"header": [
					{
						"key": "Authorization",
						"value": "Ayla-silva-banu",
						"type": "text"
					}
				],
				"body": {
					"mode": "raw",
					"raw": "",
					"options": {
						"raw": {
							"language": "json"
						}
					}
				},
				"url": {
					"raw": "https://us-central1-labenu-apis.cloudfunctions.net/labefy/playlists/search?name=\"Remix\"&=",
					"protocol": "https",
					"host": [
						"us-central1-labenu-apis",
						"cloudfunctions",
						"net"
					],
					"path": [
						"labefy",
						"playlists",
						"search"
					],
					"query": [
						{
							"key": "name",
							"value": "\"Remix\""
						},
						{
							"key": "",
							"value": ""
						}
					]
				}
			},
			"response": []
		},
		{
			"name": "deletePlaylist",
			"request": {
				"method": "DELETE",
				"header": [
					{
						"key": "Authorization",
						"value": "Ayla-silva-banu",
						"type": "text"
					}
				],
				"body": {
					"mode": "raw",
					"raw": "",
					"options": {
						"raw": {
							"language": "json"
						}
					}
				},
				"url": {
					"raw": "https://us-central1-labenu-apis.cloudfunctions.net/labefy/playlists/:playlistId",
					"protocol": "https",
					"host": [
						"us-central1-labenu-apis",
						"cloudfunctions",
						"net"
					],
					"path": [
						"labefy",
						"playlists",
						":playlistId"
					],
					"variable": [
						{
							"key": "playlistId",
							"value": "8295fd58-5460-4b2c-876c-222abed1958f"
						}
					]
				}
			},
			"response": []
		},
		{
			"name": "RemoveTrack",
			"request": {
				"method": "DELETE",
				"header": [
					{
						"key": "Authorization",
						"value": "Ayla-silva-banu",
						"type": "text"
					}
				],
				"body": {
					"mode": "raw",
					"raw": "",
					"options": {
						"raw": {
							"language": "json"
						}
					}
				},
				"url": {
					"raw": "https://us-central1-labenu-apis.cloudfunctions.net/labefy/playlists/:playlistId/tracks/:trackId",
					"protocol": "https",
					"host": [
						"us-central1-labenu-apis",
						"cloudfunctions",
						"net"
					],
					"path": [
						"labefy",
						"playlists",
						":playlistId",
						"tracks",
						":trackId"
					],
					"variable": [
						{
							"key": "playlistId",
							"value": "71cb81c8-eaeb-4874-b433-4a476ff93d37"
						},
						{
							"key": "trackId",
							"value": "42cd11be-e12a-4ef9-b856-b9991281694c"
						}
					]
				}
			},
			"response": []
		}
	]
}